dashing/__init__.py
dashing/permissions.py
dashing/settings.py
dashing/utils.py
dashing/views.py
dashing/widgets.py
dashing/static/dashing-config.js
dashing/static/dashing/dashing.css
dashing/static/dashing/dashing.js
dashing/static/dashing/dashing.utils.js
dashing/static/dashing/version.js
dashing/static/dashing/fonts/FontAwesome.otf
dashing/static/dashing/fonts/fontawesome-webfont.eot
dashing/static/dashing/fonts/fontawesome-webfont.svg
dashing/static/dashing/fonts/fontawesome-webfont.ttf
dashing/static/dashing/fonts/fontawesome-webfont.woff
dashing/static/dashing/libs/jquery-1.11.0.js
dashing/static/dashing/libs/moment-with-locales.js
dashing/static/dashing/libs/rivets.js
dashing/static/dashing/libs/sightglass.js
dashing/static/dashing/libs/d3/LICENSE
dashing/static/dashing/libs/d3/d3.js
dashing/static/dashing/libs/d3/d3.min.js
dashing/static/dashing/libs/font-awesome/font-awesome.css
dashing/static/dashing/libs/jquery-gridster/jquery.gridster.css
dashing/static/dashing/libs/jquery-gridster/jquery.gridster.js
dashing/static/dashing/libs/jquery-knob/jquery.knob.js
dashing/static/dashing/libs/jquery-knob/jquery.knob.min.js
dashing/static/dashing/libs/markerclusterer/markerclusterer.js
dashing/static/dashing/libs/markerclusterer/markerclusterer.min.js
dashing/static/dashing/libs/moment/moment.js
dashing/static/dashing/libs/moment/locale/af.js
dashing/static/dashing/libs/moment/locale/ar-ma.js
dashing/static/dashing/libs/moment/locale/ar-sa.js
dashing/static/dashing/libs/moment/locale/ar-tn.js
dashing/static/dashing/libs/moment/locale/ar.js
dashing/static/dashing/libs/moment/locale/az.js
dashing/static/dashing/libs/moment/locale/be.js
dashing/static/dashing/libs/moment/locale/bg.js
dashing/static/dashing/libs/moment/locale/bn.js
dashing/static/dashing/libs/moment/locale/bo.js
dashing/static/dashing/libs/moment/locale/br.js
dashing/static/dashing/libs/moment/locale/bs.js
dashing/static/dashing/libs/moment/locale/ca.js
dashing/static/dashing/libs/moment/locale/cs.js
django3_dashing-0.5.2.dist-info/LICENSE
django3_dashing-0.5.2.dist-info/METADATA
django3_dashing-0.5.2.dist-info/WHEEL
django3_dashing-0.5.2.dist-info/top_level.txt
django3_dashing-0.5.2.dist-info/RECORD
