Metadata-Version: 2.1
Name: django3-dashing
Version: 0.5.2
Summary: A simple Django (v3 which requires Python 3) dashboard app to visualize interesting data about your project.
Home-page: https://github.com/wickeyware/django-dashing/
Author: Michael Wickey
Author-email: wickeym@gmail.com
License: MIT License
Keywords: django,python3,metrics,dashboard,dashing,metric,widgets,data
Platform: UNKNOWN
Classifier: Environment :: Web Environment
Classifier: Framework :: Django
Classifier: Intended Audience :: Developers
Classifier: License :: OSI Approved :: MIT License
Classifier: Operating System :: OS Independent
Classifier: Programming Language :: Python
Classifier: Programming Language :: Python :: 3.6
Classifier: Programming Language :: Python :: 3.7
Classifier: Programming Language :: Python :: 3.8
Classifier: Programming Language :: Python :: 3.9
Classifier: Topic :: Internet :: WWW/HTTP
Classifier: Topic :: Internet :: WWW/HTTP :: Dynamic Content
Classifier: Topic :: Software Development :: Libraries :: Python Modules
Classifier: Topic :: Software Development :: Localization
Classifier: Topic :: Utilities
